tse_datatools/__init__.py
tse_datatools/_version.py
tse_datatools/analysis/__init__.py
tse_datatools/analysis/processor.py
tse_datatools/data/__init__.py
tse_datatools/data/actimot_data.py
tse_datatools/data/animal.py
tse_datatools/data/box.py
tse_datatools/data/calorimetry_data.py
tse_datatools/data/dataset.py
tse_datatools/data/dataset_component.py
tse_datatools/data/drinkfeed_data.py
tse_datatools/data/group.py
tse_datatools/data/variable.py
tse_datatools/data/workspace.py
tse_datatools/loaders/__init__.py
tse_datatools/loaders/actimot_data_loader.py
tse_datatools/loaders/calorimetry_data_loader.py
tse_datatools/loaders/dataset_loader.py
tse_datatools/loaders/drinkfeed_data_loader.py
tse_datatools-0.1.0.dist-info/LICENSE
tse_datatools-0.1.0.dist-info/METADATA
tse_datatools-0.1.0.dist-info/WHEEL
tse_datatools-0.1.0.dist-info/top_level.txt
tse_datatools-0.1.0.dist-info/zip-safe
tse_datatools-0.1.0.dist-info/RECORD
